continuum/__init__.py
continuum/download.py
continuum/utils.py
continuum/viz.py
continuum/datasets/__init__.py
continuum/datasets/awa2.py
continuum/datasets/base.py
continuum/datasets/birdsnap.py
continuum/datasets/caltech.py
continuum/datasets/car196.py
continuum/datasets/cifar100.py
continuum/datasets/colored_mnist.py
continuum/datasets/core50.py
continuum/datasets/ctrl.py
continuum/datasets/cub200.py
continuum/datasets/domain_net.py
continuum/datasets/dtd.py
continuum/datasets/eurosat.py
continuum/datasets/fellowship.py
continuum/datasets/fer2013.py
continuum/datasets/fgvc_aircraft.py
continuum/datasets/flowers102.py
continuum/datasets/fluentspeech.py
continuum/datasets/food101.py
continuum/datasets/gtsrb.py
continuum/datasets/imagenet.py
continuum/datasets/nlp.py
continuum/datasets/office_home.py
continuum/datasets/omniglot.py
continuum/datasets/oxford_pet.py
continuum/datasets/pacs.py
continuum/datasets/pascalvoc.py
continuum/datasets/pytorch.py
continuum/datasets/rainbow_mnist.py
continuum/datasets/stl10.py
continuum/datasets/stream51.py
continuum/datasets/sun397.py
continuum/datasets/svhn.py
continuum/datasets/synbols.py
continuum/datasets/terra_incognita.py
continuum/datasets/vlcs.py
continuum/generators/__init__.py
continuum/generators/scenarios_generator.py
continuum/metrics/__init__.py
continuum/metrics/base_logger.py
continuum/metrics/logger.py
continuum/metrics/metrics.py
continuum/metrics/utils.py
continuum/rehearsal/__init__.py
continuum/rehearsal/herding.py
continuum/rehearsal/memory.py
continuum/scenarios/__init__.py
continuum/scenarios/base.py
continuum/scenarios/class_incremental.py
continuum/scenarios/continual_scenario.py
continuum/scenarios/hashed.py
continuum/scenarios/instance_incremental.py
continuum/scenarios/online_fellowship.py
continuum/scenarios/permutations.py
continuum/scenarios/rotations.py
continuum/scenarios/scenario_utils.py
continuum/scenarios/segmentation.py
continuum/scenarios/specific_scenarios.py
continuum-1.2.4.dist-info/LICENSE
continuum-1.2.4.dist-info/METADATA
continuum-1.2.4.dist-info/WHEEL
continuum-1.2.4.dist-info/top_level.txt
continuum-1.2.4.dist-info/RECORD
