Metadata-Version: 2.1
Name: continuum
Version: 1.2.4
Summary: A clean and simple library for Continual Learning in PyTorch.
Home-page: https://github.com/Continvvm/continuum
Author: Arthur Douillard, Timothée Lesort
Author-email: ar.douillard@gmail.com
License: UNKNOWN
Platform: UNKNOWN
Classifier: Programming Language :: Python :: 3
Classifier: License :: OSI Approved :: MIT License
Classifier: Operating System :: OS Independent
Requires-Python: >=3.6
Requires-Dist: torch (>=1.2.0)
Requires-Dist: torchvision (>=0.4.0)
Requires-Dist: numpy (>=1.17.2)
Requires-Dist: Pillow (>=6.2.1)
Requires-Dist: matplotlib (>=3.1.0)
Requires-Dist: scipy (>=1.3.3)
Requires-Dist: scikit-image (>=0.15.0)
Requires-Dist: scikit-learn (>=0.24.1)
Requires-Dist: pandas (>=1.1.5)
Requires-Dist: pytest (>=5.0.1)
Requires-Dist: pytest-mock (>=3.6.1)
Requires-Dist: prospector[with_mypy] (>=1.2.0)
Requires-Dist: h5py (>=3.1.0)
Requires-Dist: requests (>=2.24.0)
Requires-Dist: ImageHash (>=4.2.1)
Requires-Dist: datasets (>=1.6.0)
